<?xml version="1.0" encoding="utf-8"?>
<Mob>
  <Drops>
    <Drop>
      <ID>1002096</ID>
      <Chance>100</Chance>
    </Drop>
    <Drop>
      <ID>1322024</ID>
      <Chance>100</Chance>
    </Drop>
    <Drop>
      <ID>1412000</ID>
      <Chance>100</Chance>
    </Drop>
    <Drop>
      <ID>1412006</ID>
      <Chance>100</Chance>
    </Drop>
    <Drop>
      <ID>1422001</ID>
      <Chance>100</Chance>
    </Drop>
    <Drop>
      <ID>1002160</ID>
      <Chance>100</Chance>
    </Drop>
    <Drop>
      <ID>1072027</ID>
      <Chance>100</Chance>
    </Drop>
    <Drop>
      <ID>1462000</ID>
      <Chance>100</Chance>
    </Drop>
    <Drop>
      <ID>1040072</ID>
      <Chance>100</Chance>
    </Drop>
    <Drop>
      <ID>1072086</ID>
      <Chance>100</Chance>
    </Drop>
    <Drop>
      <ID>1040062</ID>
      <Chance>100</Chance>
    </Drop>
    <Drop>
      <ID>1040062</ID>
      <Chance>100</Chance>
    </Drop>
    <Drop>
      <ID>1060051</ID>
      <Chance>100</Chance>
    </Drop>
    <Drop>
      <ID>2060000</ID>
      <Chance>100</Chance>
    </Drop>
    <Drop>
      <ID>2061000</ID>
      <Chance>100</Chance>
    </Drop>
    <Drop>
      <ID>2000003</ID>
      <Chance>100</Chance>
    </Drop>
    <Drop>
      <ID>2000001</ID>
      <Chance>100</Chance>
    </Drop>
    <Drop>
      <ID>2044600</ID>
      <Chance>100</Chance>
    </Drop>
    <Drop>
      <ID>2040501</ID>
      <Chance>100</Chance>
    </Drop>
    <Drop>
      <ID>4020002</ID>
      <Chance>100</Chance>
    </Drop>
    <Drop>
      <ID>4000165</ID>
      <Chance>100</Chance>
    </Drop>
    <Drop>
      <ID>4010006</ID>
      <Chance>100</Chance>
    </Drop>
    <Drop>
      <ID>4004000</ID>
      <Chance>100</Chance>
    </Drop>
    <Drop>
      <ID>4031209</ID>
      <Chance>100</Chance>
    </Drop>
    <Drop>
      <ID>4006000</ID>
      <Chance>100</Chance>
    </Drop>
  </Drops>
  <Mesos>
    <Min>52</Min>
    <Max>78</Max>
  </Mesos>
</Mob>