<?xml version="1.0" encoding="utf-8"?>
<Mob>
  <Drops>
    <Drop>
      <ID>1002021</ID>
      <Chance>100</Chance>
    </Drop>
    <Drop>
      <ID>1092029</ID>
      <Chance>100</Chance>
    </Drop>
    <Drop>
      <ID>1002143</ID>
      <Chance>100</Chance>
    </Drop>
    <Drop>
      <ID>1050036</ID>
      <Chance>100</Chance>
    </Drop>
    <Drop>
      <ID>1040076</ID>
      <Chance>100</Chance>
    </Drop>
    <Drop>
      <ID>1060065</ID>
      <Chance>100</Chance>
    </Drop>
    <Drop>
      <ID>2022251</ID>
      <Chance>100</Chance>
    </Drop>
    <Drop>
      <ID>2022250</ID>
      <Chance>100</Chance>
    </Drop>
    <Drop>
      <ID>4000018</ID>
      <Chance>100</Chance>
    </Drop>
  </Drops>
  <Mesos>
    <Min>96</Min>
    <Max>144</Max>
  </Mesos>
</Mob>